dmsh/__init__.py
dmsh/_helpers.py
dmsh/_license_validation.py
dmsh/_main.py
dmsh/py.typed
dmsh/geometry/__init__.py
dmsh/geometry/circle.py
dmsh/geometry/ellipse.py
dmsh/geometry/geometry.py
dmsh/geometry/halfspace.py
dmsh/geometry/path.py
dmsh/geometry/polygon.py
dmsh/geometry/rectangle.py
dmsh/geometry/rotation.py
dmsh/geometry/pypathlib/__init__.py
dmsh/geometry/pypathlib/closed_path.py
dmsh/geometry/pypathlib/helpers.py
dmsh/geometry/pypathlib/path.py
dmsh-0.3.4.dist-info/METADATA
dmsh-0.3.4.dist-info/WHEEL
dmsh-0.3.4.dist-info/top_level.txt
dmsh-0.3.4.dist-info/RECORD
