Metadata-Version: 2.1
Name: dmsh
Version: 0.3.4
Summary: High-quality 2D mesh generator based on distmesh
Author-email: Nico Schlömer <nico.schloemer@gmail.com>
Project-URL: Home, https://github.com/meshpro/dmsh
Project-URL: Issues, https://github.com/meshpro/dmsh/issues
Classifier: Development Status :: 4 - Beta
Classifier: License :: Other/Proprietary License
Classifier: Intended Audience :: Science/Research
Classifier: Operating System :: OS Independent
Classifier: Programming Language :: Python
Classifier: Programming Language :: Python :: 3
Classifier: Programming Language :: Python :: 3.8
Classifier: Programming Language :: Python :: 3.9
Classifier: Programming Language :: Python :: 3.10
Classifier: Programming Language :: Python :: 3.11
Classifier: Programming Language :: Python :: 3.12
Classifier: Topic :: Scientific/Engineering
Classifier: Topic :: Scientific/Engineering :: Mathematics
Requires-Python: >=3.7
Requires-Dist: x21 (>=0.5.2)
Requires-Dist: meshplex <0.20.0,>=0.16.0
Requires-Dist: npx
Requires-Dist: numpy
Requires-Dist: stonefish-license-manager
Requires-Dist: scipy
Provides-Extra: all
Requires-Dist: matplotlib ; extra == 'all'
